MANIFEST.in
requirements.txt
setup.py
clonesearch/__init__.py
clonesearch/__main__.py
clonesearch/clonesearch.py
clonesearch.egg-info/PKG-INFO
clonesearch.egg-info/SOURCES.txt
clonesearch.egg-info/dependency_links.txt
clonesearch.egg-info/entry_points.txt
clonesearch.egg-info/requires.txt
clonesearch.egg-info/top_level.txt