Metadata-Version: 1.0
Name: clonesearch
Version: 1.0
Summary: Clone Github repos based on a search query.
Home-page: https://github.com/Raynes/clonesearch
Author: Anthony Grimes
Author-email: UNKNOWN
License: MIT
Platform: UNKNOWN
